{
  "images": [
    {
      "id": "img_0001",
      "url": "https://cdn.jsdelivr.net/gh/abhishekjaiswar224-ctrl/illusion-game-images@main/img_0001.webp",
      "mode": "object",
      "question": "How many hidden objects can you find?",
      "answer": 5
    },
    {
      "id": "img_0002",
      "url": "https://cdn.jsdelivr.net/gh/abhishekjaiswar224-ctrl/illusion-game-images@main/img_0002.webp",
      "mode": "object",
      "question": "How many hidden objects can you find?",
      "answer": 5
    },
    {
      "id": "img_0003",
      "url": "https://cdn.jsdelivr.net/gh/abhishekjaiswar224-ctrl/illusion-game-images@main/img_0003.webp",
      "mode": "object",
      "question": "How many hidden objects can you find?",
      "answer": 5
    },
    {
      "id": "img_0004",
      "url": "https://cdn.jsdelivr.net/gh/abhishekjaiswar224-ctrl/illusion-game-images@main/img_0004.webp",
      "mode": "object",
      "question": "How many hidden objects can you find?",
      "answer": 5
    },
    {
      "id": "img_0005",
      "url": "https://cdn.jsdelivr.net/gh/abhishekjaiswar224-ctrl/illusion-game-images@main/img_0005.webp",
      "mode": "object",
      "question": "How many hidden objects can you find?",
      "answer": 5
    },
    {
      "id": "img_0006",
      "url": "https://cdn.jsdelivr.net/gh/abhishekjaiswar224-ctrl/illusion-game-images@main/img_0006.webp",
      "mode": "object",
      "question": "How many hidden objects can you find?",
      "answer": 5
    },
    {
      "id": "img_0007",
      "url": "https://cdn.jsdelivr.net/gh/abhishekjaiswar224-ctrl/illusion-game-images@main/img_0007.webp",
      "mode": "object",
      "question": "How many hidden objects can you find?",
      "answer": 5
    },
    {
      "id": "img_0008",
      "url": "https://cdn.jsdelivr.net/gh/abhishekjaiswar224-ctrl/illusion-game-images@main/img_0008.webp",
      "mode": "object",
      "question": "How many hidden objects can you find?",
      "answer": 5
    },
    {
      "id": "img_0009",
      "url": "https://cdn.jsdelivr.net/gh/abhishekjaiswar224-ctrl/illusion-game-images@main/img_0009.webp",
      "mode": "object",
      "question": "How many hidden objects can you find?",
      "answer": 5
    }
  ]
}